collectd_iscdhcp/__init__.py
collectd_iscdhcp/collectd_plugin.py
collectd_iscdhcp-0.1.0.data/scripts/dhcpd-pools
collectd_iscdhcp-0.1.0.dist-info/DESCRIPTION.rst
collectd_iscdhcp-0.1.0.dist-info/METADATA
collectd_iscdhcp-0.1.0.dist-info/RECORD
collectd_iscdhcp-0.1.0.dist-info/WHEEL
collectd_iscdhcp-0.1.0.dist-info/metadata.json
collectd_iscdhcp-0.1.0.dist-info/pbr.json
collectd_iscdhcp-0.1.0.dist-info/top_level.txt
