Metadata-Version: 2.0
Name: collectd-iscdhcp
Version: 0.1.0
Summary: CollectD plugin for ISC DHCP
Home-page: https://github.com/Yuav/collectd-iscdhcp
Author: Jon Skarpeteig
Author-email: jon.skarpeteig@gmail.com
License: UNKNOWN
Keywords: collectd-iscdhcp,collectd,isc,dhcp,metrics
Platform: UNKNOWN
Requires-Dist: collectd
